LICENSE
README.md
setup.py
bin/morfeus
morfeus/__init__.py
morfeus/device.py
morfeus.egg-info/PKG-INFO
morfeus.egg-info/SOURCES.txt
morfeus.egg-info/dependency_links.txt
morfeus.egg-info/not-zip-safe
morfeus.egg-info/requires.txt
morfeus.egg-info/top_level.txt