Metadata-Version: 2.1
Name: morfeus
Version: 0.3
Summary: Library to control moRFeus mixer/signal generator
Home-page: http://github.com/tai/morfeus
Author: Taisuke Yamada
Author-email: tai.nospam@nospam.rakugaki.org
License: MIT
Platform: UNKNOWN
Classifier: Programming Language :: Python :: 3
Classifier: License :: OSI Approved :: MIT License
Classifier: Operating System :: OS Independent
Classifier: Topic :: Communications :: Ham Radio
Classifier: Topic :: System :: Hardware :: Hardware Drivers
Classifier: Intended Audience :: Science/Research
Classifier: Intended Audience :: Telecommunications Industry
